myextensiondependencystrong/__init__.py
myextensiondependencystrong-0.8.0.dist-info/METADATA
myextensiondependencystrong-0.8.0.dist-info/WHEEL
myextensiondependencystrong-0.8.0.dist-info/top_level.txt
myextensiondependencystrong-0.8.0.dist-info/RECORD
