Metadata-Version: 2.4
Name: myextensiondependencystrong
Version: 0.8.0
Summary: A simple example package
Author: Erdi Aktan
Author-email: erdiaktan@gmail.com
Classifier: Programming Language :: Python :: 3
Classifier: Operating System :: OS Independent
Requires-Dist: requests
Dynamic: author
Dynamic: author-email
Dynamic: classifier
Dynamic: requires-dist
Dynamic: summary
